socketscpi/__init__.py
socketscpi/socketscpi.py
tests/__init__.py
tests/test_socketscpi.py
socketscpi-2025.2.0.dist-info/AUTHORS.rst
socketscpi-2025.2.0.dist-info/LICENSE
socketscpi-2025.2.0.dist-info/METADATA
socketscpi-2025.2.0.dist-info/WHEEL
socketscpi-2025.2.0.dist-info/top_level.txt
socketscpi-2025.2.0.dist-info/RECORD
