Metadata-Version: 2.2
Name: socketscpi
Version: 2025.2.0
Summary: socketscpi provides a robust SCPI interface to electronic test and measurement equipment via raw socket protocol, removing the requirement for VISA and improving data transfer speed over VXI-11.
Home-page: https://github.com/morgan-at-keysight/socketscpi
Author: Morgan Allison
Author-email: morgan.allison@keysight.com
Classifier: Development Status :: 4 - Beta
Classifier: Intended Audience :: Developers
Classifier: Programming Language :: Python :: 3
Classifier: Programming Language :: Python :: 3.6
Classifier: Programming Language :: Python :: 3.7
Classifier: Programming Language :: Python :: 3.8
Classifier: Programming Language :: Python :: 3.9
Requires-Python: >=3.6
License-File: LICENSE
License-File: AUTHORS.rst
Requires-Dist: numpy
